CHANGELOG.md
LISCENCE.txt
MANIFEST.in
README.md
USAGE.md
setup.py
pymeili/DF.py
pymeili/__init__.py
pymeili/beautifyplot.py
pymeili/cmapdict.py
pymeili/configure.py
pymeili/richTable.py
pymeili/upgrade.py
pymeili.egg-info/PKG-INFO
pymeili.egg-info/SOURCES.txt
pymeili.egg-info/dependency_links.txt
pymeili.egg-info/requires.txt
pymeili.egg-info/top_level.txt
pymeili/pymeili_resource/Futura_Extra_Black_font.ttf
pymeili/pymeili_resource/Futura_Heavy_font.ttf
pymeili/pymeili_resource/HarmonyOS_Sans_TC_Bold.ttf
pymeili/pymeili_resource/HarmonyOS_Sans_TC_Regular.ttf
pymeili/pymeili_resource/KleinCondensed-Medium.ttf
pymeili/pymeili_resource/OCR-A.ttf
pymeili/pymeili_resource/OCR-A_Regular.ttf
pymeili/pymeili_resource/README.md
pymeili/pymeili_resource/config.txt
pymeili/pymeili_resource/futura medium bt.ttf
pymeili/pymeili_resource/futura_medium_bt.ttf