Metadata-Version: 2.1
Name: pymeili
Version: 1.1.10
Summary: a module to beautify your python plot.
Home-page: 
Author: VVVictorZhou
Author-email: vichouro@gmail.com
License: MIT
Keywords: beautify
Classifier: Development Status :: 4 - Beta
Classifier: Intended Audience :: Developers
Classifier: Operating System :: OS Independent
Classifier: License :: OSI Approved :: MIT License
Classifier: Programming Language :: Python :: 3
